{
  "users": [
    "Previous_Speaker8408",
    "bftceo",
    "AutoModerator",
    "pacodo",
    "jwntheatx",
    "JCorazza",
    "Booouurns",
    "InnocentByestander",
    "BunkyFlintsone",
    "ChefFunk77",
    "igooverland",
    "Primetimesusa",
    "secondhandhorology",
    "Sad_Kitchen2530",
    "mrbogle",
    "Chronothrills",
    "denimdr",
    "vserduchka",
    "Hawk07tx",
    "ns160",
    "Not_a_Lefty",
    "maluzord",
    "Bola964",
    "According-Hunter8674",
    "Vandeth_Kenji",
    "Pristine_Courage_535",
    "WatchWatchesAndCars",
    "Swissra4",
    "Electronic-Lawyer-52",
    "crypt0amat00r",
    "kevin521",
    "leppapeppasueppa",
    "client42",
    "Some_Property_917",
    "aztecknightatx",
    "wizardofAwwws",
    "DRIVN_Assets",
    "Alloicious",
    "vicari41",
    "HYPERMANIAS",
    "Bmore_Mechanic",
    "dsquared24",
    "soycowboy",
    "NefariousnessBusy207",
    "Recent-Management-68",
    "rdejesus486",
    "No-Fig-2665",
    "mikeNOBES",
    "ArlingtonBeechWUS",
    "opal3",
    "JDTurkleton",
    "jsayther",
    "Timely-Mongoose-6872",
    "SeanTurk82",
    "sparty569",
    "Jack_Carver93",
    "Gallywally123",
    "Full_Television8757",
    "Iastemperor",
    "jesusplayslax",
    "noxin77",
    "someonerandomlmao",
    "jwern01",
    "Osbronx",
    "Rude-Awakening79",
    "not_impressed79",
    "Martin_020_",
    "s0nic_2",
    "29twenty",
    "215watches",
    "JDM_SEIKO_WATCH",
    "cmgold",
    "gaffs82",
    "rumfortheborder",
    "infinit9",
    "Cold-Mix5107",
    "ridethesnek",
    "Mcnulty-420",
    "Watchex_Enterprises",
    "FLYER90",
    "Grouchy_Daikon679",
    "vegchicken",
    "Jasper371",
    "TimeCapsuleTrading",
    "Alflovescats",
    "DoubleMikeNoShoot",
    "Clean_Metal3588",
    "Ok-Rutabaga-5644",
    "JPadz41",
    "Soft_Incident8543",
    "Gain-Reduction",
    "callmememaybe",
    "gutpusha",
    "breh25",
    "BarryAllen85",
    "humbucker426"
  ],
  "batch": 1,
  "user_count": 96,
  "more_available": true,
  "subreddit": "watchexchange"
}